{"processing_level_id": "2", "tags": {"edsc.extra.serverless.subset_service.echo_orders": {"data": {"updated_at": "2020-09-25T20:00:40.019Z", "id": "S1571678140-LARC_ASDC", "type": "ECHO ORDERS", "url": "https://wbs136.larc.nasa.gov/orderadapter/OrderFulfillmentService", "option_definitions": [{"id": "2D86BA00-9709-8CB9-CB0B-6A430894417A", "name": "ASDC_FTPPULL"}]}}, "edsc.extra.serverless.collection_capabilities": {"data": {"cloud_cover": true, "day_night_flag": true, "granule_online_access_flag": false, "orbit_calculated_spatial_domains": false}}}, "boxes": ["-52 -180 52 180"], "time_start": "2015-03-25T00:00:00.000Z", "dif_ids": ["CATS-ISS_L2O_D-M7.2-V2-01_05kmPro_V2-01"], "version_id": "V2-01", "updated": "2017-01-18T00:00:00.000Z", "dataset_id": "CATS-ISS Level 2 Operational Day Mode 7.2 Version 2-01 5 km Profile", "has_spatial_subsetting": true, "has_transforms": true, "associations": {"services": ["S1571678140-LARC_ASDC"]}, "has_variables": true, "data_center": "LARC_ASDC", "short_name": "CATS-ISS_L2O_D-M7.2-V2-01_05kmPro", "organizations": ["NASA/LARC/SD/ASDC"], "title": "CATS-ISS Level 2 Operational Day Mode 7.2 Version 2-01 5 km Profile", "coordinate_system": "CARTESIAN", "summary": "CATS-ISS_L2O_D-M7.2-V2-01_05kmPro is the Cloud-Aerosol Transport System (CATS) International Space Station (ISS) Level 2 Operational Day Mode 7.2 Version 2-01 5 km Profile data product. This collection spans from March 25, 2015 to October 29, 2017. CATS, which was launched on January 10, 2015, was a lidar remote sensing instrument that provided range-resolved profile measurements of atmospheric aerosols and clouds from the ISS. CATS was intended to operate on-orbit for up to three years. CATS provides vertical profiles at three wavelengths, orbiting between ~230 and ~270 miles above the Earth's surface at a 51-degree inclination with nearly a three-day repeat cycle. For the first time, scientists were able to study diurnal (day-to-night) changes in cloud and aerosol effects from space by observing the same spot on Earth at different times each day. CATS Level 2 Layer data products contain geophysical parameters and derived from Level 1 data, at 60m vertical and 5km horizontal resolution.", "has_granules": true, "time_end": "2017-10-29T23:59:59.000Z", "orbit_parameters": {}, "id": "C1424491177-LARC_ASDC", "has_formats": false, "original_format": "DIF10", "granule_count": 8849, "archive_center": "NASA/LARC/SD/ASDC", "has_temporal_subsetting": false, "browse_flag": false, "online_access_flag": true, "links": [{"rel": "http://esipfed.org/ns/fedsearch/1.1/documentation#", "hreflang": "en-US", "href": "https://cats.gsfc.nasa.gov/data/"}, {"rel": "http://esipfed.org/ns/fedsearch/1.1/documentation#", "hreflang": "en-US", "href": "https://asdc.larc.nasa.gov/documents/cats/guide/CATS_ATBD.pdf"}, {"rel": "http://esipfed.org/ns/fedsearch/1.1/documentation#", "hreflang": "en-US", "href": "https://asdc.larc.nasa.gov/project/CATS-ISS"}, {"rel": "http://esipfed.org/ns/fedsearch/1.1/documentation#", "hreflang": "en-US", "href": "https://asdc.larc.nasa.gov/documents/cats/quality_summaries/CATS_Release_Notes6_v2.pdf"}, {"rel": "http://esipfed.org/ns/fedsearch/1.1/documentation#", "hreflang": "en-US", "href": "https://cats.gsfc.nasa.gov/media/docs/CATS_Data_Products_Catalog.pdf"}, {"rel": "http://esipfed.org/ns/fedsearch/1.1/metadata#", "hreflang": "en-US", "href": "https://doi.org/10.5067/ISS/CATS/L2O_D-M7.2-V2-01_05KMPRO"}, {"rel": "http://esipfed.org/ns/fedsearch/1.1/data#", "hreflang": "en-US", "href": "https://search.earthdata.nasa.gov/search/granules?p=C1424491177-LARC_ASDC"}, {"rel": "http://esipfed.org/ns/fedsearch/1.1/metadata#", "hreflang": "en-US", "href": "https://opendap.larc.nasa.gov/opendap/CATS/L2O_D-M7.2-V2-01_05kmPro/contents.html"}, {"rel": "http://esipfed.org/ns/fedsearch/1.1/documentation#", "hreflang": "en-US", "href": "https://asdc.larc.nasa.gov/citing-data"}, {"rel": "http://esipfed.org/ns/fedsearch/1.1/documentation#", "hreflang": "en-US", "href": "https://asdc.larc.nasa.gov/documents/cats/guide/CATS_Data_Products_Catalog_R7.0.pdf"}, {"rel": "http://esipfed.org/ns/fedsearch/1.1/documentation#", "hreflang": "en-US", "href": "https://asdc.larc.nasa.gov/documents/cats/guide/CATS_Data_Products_Catalog_R6.0.pdf"}, {"rel": "http://esipfed.org/ns/fedsearch/1.1/data#", "hreflang": "en-US", "href": "https://asdc.larc.nasa.gov/data/CATS/L2O_D-M7.2-V2-01_05kmPro/"}, {"rel": "http://esipfed.org/ns/fedsearch/1.1/documentation#", "hreflang": "en-US", "href": "https://earthobservatory.nasa.gov/images/84400/dust-and-clouds-dance-over-the-sahara"}, {"rel": "http://esipfed.org/ns/fedsearch/1.1/documentation#", "hreflang": "en-US", "href": "https://earthobservatory.nasa.gov/images/84214/blue-marble-eastern-hemisphere"}, {"rel": "http://esipfed.org/ns/fedsearch/1.1/documentation#", "hreflang": "en-US", "href": "https://earthobservatory.nasa.gov/images/86286/nighttime-view-of-raung-volcanic-plume"}, {"rel": "http://esipfed.org/ns/fedsearch/1.1/documentation#", "hreflang": "en-US", "href": "https://earthobservatory.nasa.gov/images/86218/a-slice-of-cirrus"}], "cmr": {"title": "CATS-ISS Level 2 Operational Day Mode 7.2 Version 2-01 5 km Profile", "summary": "CATS-ISS_L2O_D-M7.2-V2-01_05kmPro is the Cloud-Aerosol Transport System (CATS) International Space Station (ISS) Level 2 Operational Day Mode 7.2 Version 2-01 5 km Profile data product. This collection spans from March 25, 2015 to October 29, 2017. CATS, which was launched on January 10, 2015, was a lidar remote sensing instrument that provided range-resolved profile measurements of atmospheric aerosols and clouds from the ISS. CATS was intended to operate on-orbit for up to three years. CATS provides vertical profiles at three wavelengths, orbiting between ~230 and ~270 miles above the Earth's surface at a 51-degree inclination with nearly a three-day repeat cycle. For the first time, scientists were able to study diurnal (day-to-night) changes in cloud and aerosol effects from space by observing the same spot on Earth at different times each day. CATS Level 2 Layer data products contain geophysical parameters and derived from Level 1 data, at 60m vertical and 5km horizontal resolution.", "id": "C1424491177-LARC_ASDC", "description": "CATS-ISS_L2O_D-M7.2-V2-01_05kmPro is the Cloud-Aerosol Transport System (CATS) International Space Station (ISS) Level 2 Operational Day Mode 7.2 Version 2-01 5 km Profile data product. This collection spans from March 25, 2015 to October 29, 2017. CATS, which was launched on January 10, 2015, was a lidar remote sensing instrument that provided range-resolved profile measurements of atmospheric aerosols and clouds from the ISS. CATS was intended to operate on-orbit for up to three years. CATS provides vertical profiles at three wavelengths, orbiting between ~230 and ~270 miles above the Earth's surface at a 51-degree inclination with nearly a three-day repeat cycle. For the first time, scientists were able to study diurnal (day-to-night) changes in cloud and aerosol effects from space by observing the same spot on Earth at different times each day. CATS Level 2 Layer data products contain geophysical parameters and derived from Level 1 data, at 60m vertical and 5km horizontal resolution.", "spatialExtent": "N: 52.0 S: -52.0 E: 180.0 W: -180.0", "dataFormat": null, "temporalExtent": "2015-03-25 to 2017-10-29", "Platform": "ISS", "Data Center": "NASA/LARC/SD/ASDC", "Instrument": "CATS", "Version": "V2-01", "ScienceKeywords1": "EARTH SCIENCE@ATMOSPHERE@AEROSOLS", "ScienceKeywords2": "EARTH SCIENCE@ATMOSPHERE@AEROSOLS@AEROSOL BACKSCATTER", "ScienceKeywords3": "EARTH SCIENCE@ATMOSPHERE@AEROSOLS@AEROSOL OPTICAL DEPTH/THICKNESS", "ScienceKeywords4": "EARTH SCIENCE@ATMOSPHERE@CLOUDS"}}