{"processing_level_id": "2", "tags": {"edsc.extra.serverless.subset_service.echo_orders": {"data": {"updated_at": "2020-09-25T20:00:41.978Z", "id": "S1571678140-LARC_ASDC", "type": "ECHO ORDERS", "url": "https://wbs136.larc.nasa.gov/orderadapter/OrderFulfillmentService", "option_definitions": [{"id": "2D86BA00-9709-8CB9-CB0B-6A430894417A", "name": "ASDC_FTPPULL"}]}}, "edsc.extra.serverless.collection_capabilities": {"data": {"cloud_cover": true, "day_night_flag": true, "granule_online_access_flag": false, "orbit_calculated_spatial_domains": false}}}, "boxes": ["-90 -180 90 180"], "time_start": "2015-06-13T00:00:00.000Z", "dif_ids": ["DSCOVR_EPIC_L2_MAIAC_01"], "version_id": "01", "updated": "2017-06-13T00:00:00.000Z", "dataset_id": "DSCOVR EPIC L2 MAIAC Atmospheric Correction data product", "has_spatial_subsetting": true, "has_transforms": true, "associations": {"services": ["S1571678140-LARC_ASDC"]}, "has_variables": true, "data_center": "LARC_ASDC", "short_name": "DSCOVR_EPIC_L2_MAIAC", "organizations": ["NASA/LARC/SD/ASDC"], "title": "DSCOVR EPIC L2 MAIAC Atmospheric Correction data product", "coordinate_system": "CARTESIAN", "summary": "The Level 2 Multi-Angle Implementation of Atmospheric Correction (MAIAC) product contains atmospherically corrected spectral bidirectional reflectance factors (BRF, or surface reflectance) and bidirectional reflectance distribution function (BRDF) represented by 3 parameters of the Ross-Thick Li-Sparse model. It also provides several atmospheric quantities including cloud mask and aerosol optical depth (AOD) required for atmospheric correction. The parameters are distributed at 10 km sinusoidal grid and 1 to 2-hour temporal frequency. The atmospherically corrected surface reflectance and BRDF are fundamental quantities for climate modeling and vegetation studies. They are also important input to the Deep Space Climate Observatory (DSCOVR) Earth Polychromatic Imaging Camera (EPIC) Vegetation Earth System Data Record (VESDR) product. Due to high temporal and full disk global coverage, MAIAC EPIC AOD is a useful complementary dataset to MODIS and VIIRS global aerosol products.", "has_granules": true, "orbit_parameters": {}, "id": "C1451664065-LARC_ASDC", "has_formats": false, "original_format": "DIF10", "granule_count": 18904, "archive_center": "NASA/LARC/SD/ASDC", "has_temporal_subsetting": false, "browse_flag": true, "online_access_flag": true, "links": [{"rel": "http://esipfed.org/ns/fedsearch/1.1/documentation#", "hreflang": "en-US", "href": "https://doi.org/10.5067/EPIC/DSCOVR/L2_MAIAC.001"}, {"rel": "http://esipfed.org/ns/fedsearch/1.1/browse#", "hreflang": "en-US", "href": "https://epic.gsfc.nasa.gov"}, {"rel": "http://esipfed.org/ns/fedsearch/1.1/documentation#", "hreflang": "en-US", "href": "https://eosweb.larc.nasa.gov/citing-asdc-data"}, {"rel": "http://esipfed.org/ns/fedsearch/1.1/metadata#", "hreflang": "en-US", "href": "https://eosweb.larc.nasa.gov/project/dscovr/dscovr_epic_l2_maiac_01"}, {"rel": "http://esipfed.org/ns/fedsearch/1.1/metadata#", "hreflang": "en-US", "href": "https://opendap.larc.nasa.gov/opendap/hyrax/DSCOVR/EPIC/MAIAC/contents.html"}, {"rel": "http://esipfed.org/ns/fedsearch/1.1/documentation#", "hreflang": "en-US", "href": "https://eosweb.larc.nasa.gov/project/dscovr/EPICSO2_L2_summary_final.pdf"}, {"rel": "http://esipfed.org/ns/fedsearch/1.1/documentation#", "hreflang": "en-US", "href": "https://www.atmos-meas-tech.net/11/177/2018/amt-11-177-2018-discussion.html"}, {"rel": "http://esipfed.org/ns/fedsearch/1.1/documentation#", "hreflang": "en-US", "href": "https://eosweb.larc.nasa.gov/project/dscovr/DSCOVR_overview_2016-06-29.pdf"}, {"rel": "http://esipfed.org/ns/fedsearch/1.1/data#", "hreflang": "en-US", "href": "https://search.earthdata.nasa.gov/search/project?p=!C1451664065-LARC_ASDC"}, {"rel": "http://esipfed.org/ns/fedsearch/1.1/documentation#", "hreflang": "en-US", "href": "https://eosweb.larc.nasa.gov/project/dscovr/DSCOVR_EPIC_Geolocation_V02.pdf"}, {"rel": "http://esipfed.org/ns/fedsearch/1.1/documentation#", "hreflang": "en-US", "href": "https://eosweb.larc.nasa.gov/project/dscovr/EPIC_Data_Format_Control_Book_2016-07-01.pdf"}, {"rel": "http://esipfed.org/ns/fedsearch/1.1/documentation#", "hreflang": "en-US", "href": "https://eosweb.larc.nasa.gov/project/dscovr/featured_articles"}], "cmr": {"title": "DSCOVR EPIC L2 MAIAC Atmospheric Correction data product", "summary": "The Level 2 Multi-Angle Implementation of Atmospheric Correction (MAIAC) product contains atmospherically corrected spectral bidirectional reflectance factors (BRF, or surface reflectance) and bidirectional reflectance distribution function (BRDF) represented by 3 parameters of the Ross-Thick Li-Sparse model. It also provides several atmospheric quantities including cloud mask and aerosol optical depth (AOD) required for atmospheric correction. The parameters are distributed at 10 km sinusoidal grid and 1 to 2-hour temporal frequency. The atmospherically corrected surface reflectance and BRDF are fundamental quantities for climate modeling and vegetation studies. They are also important input to the Deep Space Climate Observatory (DSCOVR) Earth Polychromatic Imaging Camera (EPIC) Vegetation Earth System Data Record (VESDR) product. Due to high temporal and full disk global coverage, MAIAC EPIC AOD is a useful complementary dataset to MODIS and VIIRS global aerosol products.", "id": "C1451664065-LARC_ASDC", "description": "The Level 2 Multi-Angle Implementation of Atmospheric Correction (MAIAC) product contains atmospherically corrected spectral bidirectional reflectance factors (BRF, or surface reflectance) and bidirectional reflectance distribution function (BRDF) represented by 3 parameters of the Ross-Thick Li-Sparse model. It also provides several atmospheric quantities including cloud mask and aerosol optical depth (AOD) required for atmospheric correction. The parameters are distributed at 10 km sinusoidal grid and 1 to 2-hour temporal frequency. The atmospherically corrected surface reflectance and BRDF are fundamental quantities for climate modeling and vegetation studies. They are also important input to the Deep Space Climate Observatory (DSCOVR) Earth Polychromatic Imaging Camera (EPIC) Vegetation Earth System Data Record (VESDR) product. Due to high temporal and full disk global coverage, MAIAC EPIC AOD is a useful complementary dataset to MODIS and VIIRS global aerosol products.", "spatialExtent": "N: 90.0 S: -90.0 E: 180.0 W: -180.0", "dataFormat": null, "temporalExtent": "2015-06-13 to 2018-12-31", "Platform": "DSCOVR", "Data Center": "NASA/LARC/SD/ASDC", "Instrument": "EPIC", "Version": "01", "ScienceKeywords1": "EARTH SCIENCE@ATMOSPHERE@AEROSOLS", "ScienceKeywords2": "EARTH SCIENCE@ATMOSPHERE@ATMOSPHERIC CHEMISTRY", "ScienceKeywords3": "EARTH SCIENCE@ATMOSPHERE@ATMOSPHERIC PRESSURE", "ScienceKeywords4": "EARTH SCIENCE@ATMOSPHERE@CLOUDS"}}