{"processing_level_id": "3C", "tags": {"edsc.extra.serverless.collection_capabilities": {"data": {"cloud_cover": true, "day_night_flag": false, "granule_online_access_flag": true, "orbit_calculated_spatial_domains": true}}}, "boxes": ["-60 -60 60 60"], "time_start": "2004-01-19T11:30:48.000Z", "version_id": "1.0", "updated": "2018-07-26T21:35:22.956Z", "dataset_id": "GHRSST L3C OSISAF reprocessed  SSTskin dataset v1.0 from SEVIRI on MSG for Atlantic (GDS V2)", "has_spatial_subsetting": false, "has_transforms": false, "has_variables": false, "data_center": "PODAAC", "short_name": "SEVIRI_SST_DR-OSISAF-L3C-v1.0a", "organizations": ["NASA/JPL/PODAAC", "EUMETSAT"], "title": "GHRSST L3C OSISAF reprocessed  SSTskin dataset v1.0 from SEVIRI on MSG for Atlantic (GDS V2)", "coordinate_system": "CARTESIAN", "summary": "A Group for High Resolution Sea Surface Temperature (GHRSST) dataset for the Eastern Atlantic Region from the Spinning Enhanced Visible and InfraRed Imager (SEVIRI) on the MSG satellites (Meteosat-8 and Meteosat-9). The European Organization for the Exploitation of Meteorological Satellites (EUMETSAT),\nOcean and Sea Ice Satellite Application Facility (OSI SAF) has reprocessed SST products in (long) delayed-mode from MSG/SEVIRI. SST is retrieved from the SEVIRI infrared channels (10.8 and 12.0 micrometer) using a multispectral algorithm and the cloud mask (CM) from OSI SAF.  Atmospheric profiles of water vapor and temperature from a numerical weather prediction (NWP) model, OSTIA Sea Surface Temperature re-analysis and analysis, together with a radiatiave transfer model (RTTOV), are used to correct the multispectral algorithm for regional and seasonal biases due to changing atmospheric conditions.  Every 15 minutes slot is processed at full satellite resolution. The operational products are then produced by remapping over a 0.05 degree regular grid (60S-60N and 60W-60E) SST fields obtained by aggregating all 15 minute SST data available in one hour time, and the priority being given to the value the closest in time to the product nominal hour. The product format is compliant with the GHRSST Data Specification (GDS) version 2.", "has_granules": true, "time_end": "2012-12-31T23:26:59.000Z", "orbit_parameters": {}, "id": "C1661293061-PODAAC", "has_formats": false, "original_format": "UMM_JSON", "granule_count": 77396, "archive_center": "NASA/JPL/PODAAC", "has_temporal_subsetting": false, "browse_flag": true, "online_access_flag": true, "links": [{"rel": "http://esipfed.org/ns/fedsearch/1.1/metadata#", "hreflang": "en-US", "href": "http://www.ghrsst.org"}, {"rel": "http://esipfed.org/ns/fedsearch/1.1/metadata#", "hreflang": "en-US", "href": "https://podaac-tools.jpl.nasa.gov/drive/files/allData/ghrsst/sw/generic_nc_readers"}, {"rel": "http://esipfed.org/ns/fedsearch/1.1/metadata#", "hreflang": "en-US", "href": "http://www.osi-saf.org/biblio/docs/ss1_pum_leo_sst_2_0.pdf"}, {"length": "0.0KB", "rel": "http://esipfed.org/ns/fedsearch/1.1/data#", "hreflang": "en-US", "href": "https://thredds.jpl.nasa.gov/thredds/catalog_ghrsst_gds2.html?dataset=SEVIRI_SST_DR-OSISAF-L3C-v1.0a"}, {"rel": "http://esipfed.org/ns/fedsearch/1.1/browse#", "hreflang": "en-US", "href": "https://podaac.jpl.nasa.gov/Podaac/thumbnails/SEVIRI_SST_DR-OSISAF-L3C-v1.0a.jpg"}, {"length": "0.0KB", "rel": "http://esipfed.org/ns/fedsearch/1.1/data#", "hreflang": "en-US", "href": "https://podaac.jpl.nasa.gov/ws/search/granule/?datasetId=PODAAC-GHSEV-3COR1"}, {"rel": "http://esipfed.org/ns/fedsearch/1.1/documentation#", "hreflang": "en-US", "href": "https://ghrsst.jpl.nasa.gov"}, {"length": "0.0KB", "rel": "http://esipfed.org/ns/fedsearch/1.1/data#", "hreflang": "en-US", "href": "https://podaac-tools.jpl.nasa.gov/drive/files/allData/ghrsst/data/GDS2/L3C/ATLANTIC/SEVIRI/OSISAF/v1.0a"}, {"rel": "http://esipfed.org/ns/fedsearch/1.1/metadata#", "hreflang": "en-US", "href": "https://podaac-opendap.jpl.nasa.gov/opendap/allData/ghrsst/data/GDS2/L3C/ATLANTIC/SEVIRI/OSISAF/v1.0a/"}, {"rel": "http://esipfed.org/ns/fedsearch/1.1/documentation#", "hreflang": "en-US", "href": "https://podaac.jpl.nasa.gov/CitingPODAAC"}], "cmr": {"title": "GHRSST L3C OSISAF reprocessed  SSTskin dataset v1.0 from SEVIRI on MSG for Atlantic (GDS V2)", "summary": "A Group for High Resolution Sea Surface Temperature (GHRSST) dataset for the Eastern Atlantic Region from the Spinning Enhanced Visible and InfraRed Imager (SEVIRI) on the MSG satellites (Meteosat-8 and Meteosat-9). The European Organization for the Exploitation of Meteorological Satellites (EUMETSAT),\nOcean and Sea Ice Satellite Application Facility (OSI SAF) has reprocessed SST products in (long) delayed-mode from MSG/SEVIRI. SST is retrieved from the SEVIRI infrared channels (10.8 and 12.0 micrometer) using a multispectral algorithm and the cloud mask (CM) from OSI SAF.  Atmospheric profiles of water vapor and temperature from a numerical weather prediction (NWP) model, OSTIA Sea Surface Temperature re-analysis and analysis, together with a radiatiave transfer model (RTTOV), are used to correct the multispectral algorithm for regional and seasonal biases due to changing atmospheric conditions.  Every 15 minutes slot is processed at full satellite resolution. The operational products are then produced by remapping over a 0.05 degree regular grid (60S-60N and 60W-60E) SST fields obtained by aggregating all 15 minute SST data available in one hour time, and the priority being given to the value the closest in time to the product nominal hour. The product format is compliant with the GHRSST Data Specification (GDS) version 2.", "id": "C1661293061-PODAAC", "description": "A Group for High Resolution Sea Surface Temperature (GHRSST) dataset for the Eastern Atlantic Region from the Spinning Enhanced Visible and InfraRed Imager (SEVIRI) on the MSG satellites (Meteosat-8 and Meteosat-9). The European Organization for the Exploitation of Meteorological Satellites (EUMETSAT),\nOcean and Sea Ice Satellite Application Facility (OSI SAF) has reprocessed SST products in (long) delayed-mode from MSG/SEVIRI. SST is retrieved from the SEVIRI infrared channels (10.8 and 12.0 micrometer) using a multispectral algorithm and the cloud mask (CM) from OSI SAF.  Atmospheric profiles of water vapor and temperature from a numerical weather prediction (NWP) model, OSTIA Sea Surface Temperature re-analysis and analysis, together with a radiatiave transfer model (RTTOV), are used to correct the multispectral algorithm for regional and seasonal biases due to changing atmospheric conditions.  Every 15 minutes slot is processed at full satellite resolution. The operational products are then produced by remapping over a 0.05 degree regular grid (60S-60N and 60W-60E) SST fields obtained by aggregating all 15 minute SST data available in one hour time, and the priority being given to the value the closest in time to the product nominal hour. The product format is compliant with the GHRSST Data Specification (GDS) version 2.", "spatialExtent": "N: 60 S: -60 E: 60.0 W: -60.0", "dataFormat": null, "temporalExtent": "2004-01-19 to 2012-12-31", "Platform": "MSG2", "Data Center": "NASA/JPL/PODAAC, NASA/JPL/PODAAC", "Instrument": "SEVIRI", "Version": "1.0", "ScienceKeywords1": "EARTH SCIENCE@OCEANS@OCEAN TEMPERATURE@SEA SURFACE TEMPERATURE@SUBSKIN SEA SURFACE TEMPERATURE", "ScienceKeywords2": null, "ScienceKeywords3": null, "ScienceKeywords4": null}}