{"processing_level_id": "4", "tags": {"org.ceos.wgiss.cwic.granules.prod": {}, "edsc.extra.serverless.collection_capabilities": {"data": {"cloud_cover": true, "day_night_flag": true, "granule_online_access_flag": true, "orbit_calculated_spatial_domains": false}}}, "boxes": ["10 -170 84 -50"], "time_start": "1998-01-01T00:00:00.000Z", "version_id": "1", "updated": "2019-04-15T18:39:57.000Z", "dataset_id": "NACP Site: Terrestrial Biosphere Model and Aggregated Flux Data in Standard Format", "has_spatial_subsetting": true, "has_transforms": true, "associations": {"services": ["S1569163021-ORNL_DAAC"]}, "has_variables": true, "data_center": "ORNL_DAAC", "short_name": "NACP_SITE_MODEL_FLUX_STD_FMT_1183", "organizations": ["ORNL_DAAC"], "title": "NACP Site: Terrestrial Biosphere Model and Aggregated Flux Data in Standard Format", "coordinate_system": "CARTESIAN", "summary": "This data set provides standardized output variables for gross primary productivity (GPP), net ecosystem exchange (NEE), leaf area index (LAI), ecosystem respiration (Re), latent heat flux (LE), and sensible heat flux (H) from 24 terrestrial biosphere models for 47 eddy covariance flux tower sites in North America. Each model used standardized input data for each flux tower site (i.e., gap-filled, locally observed weather; land use history; and other site specific data) and followed standard model setup and spinup procedures. The files also contain gap-filled observations and total uncertainty estimates. The data set was compiled for the North American Carbon Program (NACP) Site-Level Synthesis for use in model inter-comparison and assessment of how well the models simulate carbon processes across vegetation types and environmental conditions in North America. There is one compressed (.zip) file with this data set. When expanded, the .zip file contains model output data for one variable at one site. The model output and observations are available at the native half-hourly time step, or in daily, monthly, and annual aggregations, in comma-separated text (.csv) format. ", "has_granules": true, "time_end": "2007-12-31T23:59:59.000Z", "orbit_parameters": {}, "id": "C179125665-ORNL_DAAC", "has_formats": false, "original_format": "ECHO10", "granule_count": 1, "archive_center": "ORNL_DAAC", "has_temporal_subsetting": false, "browse_flag": true, "online_access_flag": true, "links": [{"rel": "http://esipfed.org/ns/fedsearch/1.1/data#", "hreflang": "en-US", "href": "https://daac.ornl.gov/daacdata/nacp/NACP_Site_Model_Flux_Std_Fmt//"}, {"rel": "http://esipfed.org/ns/fedsearch/1.1/documentation#", "hreflang": "en-US", "href": "https://daac.ornl.gov/NACP/guides/NACP_Site_Model_Flux_Std_Fmt.html"}, {"rel": "http://esipfed.org/ns/fedsearch/1.1/metadata#", "hreflang": "en-US", "href": "https://doi.org/10.3334/ORNLDAAC/1183"}, {"rel": "http://esipfed.org/ns/fedsearch/1.1/documentation#", "hreflang": "en-US", "href": "https://daac.ornl.gov/daacdata/nacp/NACP_Site_Model_Flux_Std_Fmt//comp/figures.zip"}, {"rel": "http://esipfed.org/ns/fedsearch/1.1/documentation#", "hreflang": "en-US", "href": "https://daac.ornl.gov/daacdata/nacp/NACP_Site_Model_Flux_Std_Fmt//comp/figures_readme.pdf"}, {"rel": "http://esipfed.org/ns/fedsearch/1.1/documentation#", "hreflang": "en-US", "href": "https://daac.ornl.gov/daacdata/nacp/NACP_Site_Model_Flux_Std_Fmt//comp/NACP_Site_Model_Flux_Std_Fmt.pdf"}, {"rel": "http://esipfed.org/ns/fedsearch/1.1/documentation#", "hreflang": "en-US", "href": "https://daac.ornl.gov/daacdata/nacp/NACP_Site_Model_Flux_Std_Fmt//comp/NACP_uncertainty_analysis.pdf"}, {"rel": "http://esipfed.org/ns/fedsearch/1.1/documentation#", "hreflang": "en-US", "href": "https://daac.ornl.gov/daacdata/nacp/NACP_Site_Model_Flux_Std_Fmt//comp/Richardson_gap_filling_2009.pdf"}, {"rel": "http://esipfed.org/ns/fedsearch/1.1/documentation#", "hreflang": "en-US", "href": "https://daac.ornl.gov/daacdata/nacp/NACP_Site_Model_Flux_Std_Fmt//comp/site_information_basic.csv"}, {"rel": "http://esipfed.org/ns/fedsearch/1.1/documentation#", "hreflang": "en-US", "href": "https://daac.ornl.gov/daacdata/nacp/NACP_Site_Model_Flux_Std_Fmt//comp/site_information_extended.pdf"}, {"rel": "http://esipfed.org/ns/fedsearch/1.1/documentation#", "hreflang": "en-US", "href": "https://daac.ornl.gov/daacdata/nacp/NACP_Site_Model_Flux_Std_Fmt//comp/site_location_summary.csv"}, {"rel": "http://esipfed.org/ns/fedsearch/1.1/documentation#", "hreflang": "en-US", "href": "https://daac.ornl.gov/daacdata/nacp/NACP_Site_Model_Flux_Std_Fmt//comp/site_synthesis_protocol_v7.pdf"}, {"rel": "http://esipfed.org/ns/fedsearch/1.1/browse#", "hreflang": "en-US", "href": "https://daac.ornl.gov/graphics/browse/project/square/nacp_logo_square.png"}], "cmr": {"title": "NACP Site: Terrestrial Biosphere Model and Aggregated Flux Data in Standard Format", "summary": "This data set provides standardized output variables for gross primary productivity (GPP), net ecosystem exchange (NEE), leaf area index (LAI), ecosystem respiration (Re), latent heat flux (LE), and sensible heat flux (H) from 24 terrestrial biosphere models for 47 eddy covariance flux tower sites in North America. Each model used standardized input data for each flux tower site (i.e., gap-filled, locally observed weather; land use history; and other site specific data) and followed standard model setup and spinup procedures. The files also contain gap-filled observations and total uncertainty estimates. The data set was compiled for the North American Carbon Program (NACP) Site-Level Synthesis for use in model inter-comparison and assessment of how well the models simulate carbon processes across vegetation types and environmental conditions in North America. There is one compressed (.zip) file with this data set. When expanded, the .zip file contains model output data for one variable at one site. The model output and observations are available at the native half-hourly time step, or in daily, monthly, and annual aggregations, in comma-separated text (.csv) format. ", "id": "C179125665-ORNL_DAAC", "description": "This data set provides standardized output variables for gross primary productivity (GPP), net ecosystem exchange (NEE), leaf area index (LAI), ecosystem respiration (Re), latent heat flux (LE), and sensible heat flux (H) from 24 terrestrial biosphere models for 47 eddy covariance flux tower sites in North America. Each model used standardized input data for each flux tower site (i.e., gap-filled, locally observed weather; land use history; and other site specific data) and followed standard model setup and spinup procedures. The files also contain gap-filled observations and total uncertainty estimates. The data set was compiled for the North American Carbon Program (NACP) Site-Level Synthesis for use in model inter-comparison and assessment of how well the models simulate carbon processes across vegetation types and environmental conditions in North America. There is one compressed (.zip) file with this data set. When expanded, the .zip file contains model output data for one variable at one site. The model output and observations are available at the native half-hourly time step, or in daily, monthly, and annual aggregations, in comma-separated text (.csv) format. ", "spatialExtent": "N: 84.0 S: 10.0 E: -50.0 W: -170.0", "dataFormat": null, "temporalExtent": "1998-01-01 to 2007-12-31", "Platform": "NOT APPLICABLE", "Data Center": "ORNL_DAAC", "Instrument": "NOT APPLICABLE", "Version": "1", "ScienceKeywords1": "EARTH SCIENCE@BIOSPHERE@ECOLOGICAL DYNAMICS@ECOSYSTEM FUNCTIONS", "ScienceKeywords2": "EARTH SCIENCE@BIOSPHERE@ECOSYSTEMS@ANTHROPOGENIC/HUMAN INFLUENCED ECOSYSTEMS@AGRICULTURAL LANDS", "ScienceKeywords3": "EARTH SCIENCE@BIOSPHERE@ECOSYSTEMS@AQUATIC ECOSYSTEMS@WETLANDS", "ScienceKeywords4": "EARTH SCIENCE@BIOSPHERE@ECOSYSTEMS@TERRESTRIAL ECOSYSTEMS@ALPINE/TUNDRA"}, "citation": ["Peng, L., Z. Zeng, Z. Wei, A. Chen, E.F. Wood, and J. Sheffield. 2019. Determinants of the ratio of actual to potential evapotranspiration. Global Change Biology. 25(4):1326-1343.", "Stoy, P.C., T.S. El-Madany, J.B. Fisher, P. Gentine, T. Gerken, S.P. Good, A. Klosterhalfen, S. Liu, D.G. Miralles, O. Perez-Priego, A.J. Rigden, T.H. Skaggs, G. Wohlfahrt, R.G. Anderson, A.M.J. Coenders-Gerrits, M. Jung, W.H. Maes, I. Mammarella, M. Mauder, M. Migliavacca, J.A. Nelson, R. Poyatos, M. Reichstein, R.L. Scott, and S. Wolf. 2019. Reviews and syntheses: Turning the challenges of partitioning ecosystem evaporation and transpiration into opportunities. Biogeosciences. 16(19):3747-3775.", "Cook, R.B., Y. Wei, L.A. Hook, S.K.S. Vannan, and J.J. McNelis 2018. Preserve: Protecting Data for Long-Term Use. Ecological Informatics.", "Raczka, B., M.C. Dietze, S.P. Serbin, and K.J. Davis. 2018. What Limits Predictive Certainty of Long-Term Carbon Uptake?. Journal of Geophysical Research: Biogeosciences. 123(12):3570-3588.", "Lu, D., D. Ricciuto, A. Walker, C. Safta, and W. Munger. 2017. Bayesian calibration of terrestrial ecosystem models: a study of advanced Markov chain Monte Carlo methods. Biogeosciences. 14(18):4295-4314.", "Lokupitiya, E., A.S. Denning, K. Schaefer, D. Ricciuto, R. Anderson, M.A. Arain, I. Baker, A.G. Barr, G. Chen, J.M. Chen, P. Ciais, D.R. Cook, M. Dietze, M. El Maayar, M. Fischer, R. Grant, D. Hollinger, C. Izaurralde, A. Jain, C. Kucharik, Z. Li, S. Liu, L. Li, R. Matamala, P. Peylin, D. Price, S.W. Running, A. Sahoo, M. Sprintsin, A.E. Suyker, H. Tian, C. Tonitto, M. Torn, H. Verbeeck, S.B. Verma, and Y. Xue. 2016. Carbon and energy fluxes in cropland ecosystems: a model-data comparison. Biogeochemistry. 129(1-2):53-76.", "Mao, J., W. Fu, X. Shi, D.M. Ricciuto, J.B. Fisher, R.E. Dickinson, Y. Wei, W. Shem, S. Piao, K. Wang, C.R. Schwalm, H. Tian, M. Mu, A. Arain, P. Ciais, R. Cook, Y. Dai, D. Hayes, F.M. Hoffman, M. Huang, S. Huang, D.N. Huntzinger, A. Ito, A. Jain, A.W. King, H. Lei, C. Lu, A.M. Michalak, N. Parazoo, C. Peng, S. Peng, B. Poulter, K. Schaefer, E. Jafarov, P.E. Thornton, W. Wang, N. Zeng, Z. Zeng, F. Zhao, Q. Zhu, and Z. Zhu. 2015. Disentangling climatic and anthropogenic controls on global terrestrial evapotranspiration trends. Environmental Research Letters. 10(9):094008.", "Wang, H.J., W.J. Riley, and W.D. Collins. 2015. Statistical uncertainty of eddy covariance CO 2 fluxes inferred using a residual bootstrap approach. Agricultural and Forest Meteorology. 206:163-171.", "Keenan, T.F., J. Gray, M.A. Friedl, M. Toomey, G. Bohrer, D.Y. Hollinger, J.W. Munger, J. O'Keefe, H.P. Schmid, I.S. Wing, B. Yang, and A.D. Richardson. 2014. Net carbon uptake has increased through warming-induced changes in temperate forest phenology. Nature Climate Change. 4(7):598-604.", "Barr, A.G., A.D. Richardson, D.Y. Hollinger, D. Papale, M.A. Arain, T.A. Black, G. Bohrer, D. Dragoni, M.L. Fischer, L. Gu, B.E. Law, H.A. Margolis, J.H. McCaughey, J.W. Munger, W. Oechel, and K. Schaeffer. 2013. Use of change-point detection for friction-velocity threshold evaluation in eddy-covariance studies. Agricultural and Forest Meteorology. 171-172:31-45.", "Keenan, T.F., D.Y. Hollinger, G. Bohrer, D. Dragoni, J.W. Munger, H.P. Schmid, and A.D. Richardson. 2013. Increase in forest water-use efficiency as atmospheric carbon dioxide concentrations rise. Nature. 499(7458):324-327.", "Raczka, B.M., K.J. Davis, D. Huntzinger, R.P. Neilson, B. Poulter, A.D. Richardson, J. Xiao, I. Baker, P. Ciais, T.F. Keenan, B. Law, W.M. Post, D. Ricciuto, K. Schaefer, H. Tian, E. Tomelleri, H. Verbeeck, and N. Viovy. 2013. Evaluation of continental carbon cycle simulations with North American flux tower observations. Ecological Monographs. 83(4):531-556.", "Stoy, P.C., M.C. Dietze, A.D. Richardson, R. Vargas, A.G. Barr, R.S. Anderson, M.A. Arain, I.T. Baker, T.A. Black, J.M. Chen, R.B. Cook, C.M. Gough, R.F. Grant, D.Y. Hollinger, R.C. Izaurralde, C.J. Kucharik, P. Lafleur, B.E. Law, S. Liu, E. Lokupitiya, Y. Luo, J.W. Munger, C. Peng, B. Poulter, D.T. Price, D.M. Ricciuto, W.J. Riley, A.K. Sahoo, K. Schaefer, C.R. Schwalm, H. Tian, H. Verbeeck, and E. Weng. 2013. Evaluating the agreement between measurements and models of net ecosystem exchange at different times and timescales using wavelet coherence: an example using data from the North American Carbon Program Site-Level Interim Synthesis. Biogeosciences. 10(11):6893-6909.", "Vizcarra, Natasha. (2013) The secrets of leaves", "Keenan, T.F., I. Baker, A. Barr, P. Ciais, K. Davis, M. Dietze, D. Dragoni, C.M. Gough, R. Grant, D. Hollinger, K. Hufkens, B. Poulter, H. McCaughey, B. Raczka, Y. Ryu, K. Schaefer, H. Tian, H. Verbeeck, M. Zhao, and A.D. Richardson. 2012. Terrestrial biosphere model performance for inter-annual variability of land-atmosphere CO2 exchange. Global Change Biology. 18(6):1971-1987.", "Richardson, A.D., R.S. Anderson, M.A. Arain, A.G. Barr, G. Bohrer, G. Chen, J.M. Chen, P. Ciais, K.J. Davis, A.R. Desai, M.C. Dietze, D. Dragoni, S.R. Garrity, C.M. Gough, R. Grant, D.Y. Hollinger, H.A. Margolis, H. McCaughey, M. Migliavacca, R.K. Monson, J.W. Munger, B. Poulter, B.M. Raczka, D.M. Ricciuto, A.K. Sahoo, K. Schaefer, H. Tian, R. Vargas, H. Verbeeck, J. Xiao, and Y. Xue. 2012. Terrestrial biosphere models need better representation of vegetation phenology: results from the North American Carbon Program Site Synthesis. Global Change Biology. 18(2):566-584.", "Schaefer, K., C.R. Schwalm, C. Williams, M.A. Arain, A. Barr, J.M. Chen, K.J. Davis, D. Dimitrov, T.W. Hilton, D.Y. Hollinger, E. Humphreys, B. Poulter, B.M. Raczka, A.D. Richardson, A. Sahoo, P. Thornton, R. Vargas, H. Verbeeck, R. Anderson, I. Baker, T.A. Black, P. Bolstad, J. Chen, P.S. Curtis, A.R. Desai, M. Dietze, D. Dragoni, C. Gough, R.F. Grant, L. Gu, A. Jain, C. Kucharik, B. Law, S. Liu, E. Lokipitiya, H.A. Margolis, R. Matamala, J.H. McCaughey, R. Monson, J.W. Munger, W. Oechel, C. Peng, D.T. Price, D. Ricciuto, W.J. Riley, N. Roulet, H. Tian, C. Tonitto, M. Torn, E. Weng, and X. Zhou. 2012. A model-data comparison of gross primary productivity: Results from the North American Carbon Program site synthesis. Journal of Geophysical Research: Biogeosciences. 117(G3):n/a-n/a.", "Dietze, M.C., R. Vargas, A.D. Richardson, P.C. Stoy, A.G. Barr, R.S. Anderson, M.A. Arain, I.T. Baker, T.A. Black, J.M. Chen, P. Ciais, L.B. Flanagan, C.M. Gough, R.F. Grant, D. Hollinger, R.C. Izaurralde, C.J. Kucharik, P. Lafleur, S. Liu, E. Lokupitiya, Y. Luo, J.W. Munger, C. Peng, B. Poulter, D.T. Price, D.M. Ricciuto, W.J. Riley, A.K. Sahoo, K. Schaefer, A.E. Suyker, H. Tian, C. Tonitto, H. Verbeeck, S.B. Verma, W. Wang, and E. Weng. 2011. Characterizing the performance of ecosystem models across time scales: A spectral analysis of the North American Carbon Program site-level synthesis. Journal of Geophysical Research. 116(G4):", "Schwalm, C.R., C.A. Williams, K. Schaefer, R. Anderson, M.A. Arain, I. Baker, A. Barr, T.A. Black, G. Chen, J.M. Chen, P. Ciais, K.J. Davis, A. Desai, M. Dietze, D. Dragoni, M.L. Fischer, L.B. Flanagan, R. Grant, L. Gu, D. Hollinger, R.C. Izaurralde, C. Kucharik, P. Lafleur, B.E. Law, L. Li, Z. Li, S. Liu, E. Lokupitiya, Y. Luo, S. Ma, H. Margolis, R. Matamala, H. McCaughey, R.K. Monson, W.C. Oechel, C. Peng, B. Poulter, D.T. Price, D.M. Riciutto, W. Riley, A.K. Sahoo, M. Sprintsin, J. Sun, H. Tian, C. Tonitto, H. Verbeeck, and S.B. Verma. 2010. A model-data intercomparison of CO2exchange across North America: Results from the North American Carbon Program site synthesis. Journal of Geophysical Research. 115:"], "doi": ["https://doi.org/10.1111/gcb.14577", "https://doi.org/10.5194/bg-16-3747-2019", "NA", "https://doi.org/10.1029/2018JG004504", "https://doi.org/10.5194/bg-14-4295-2017", "https://doi.org/10.1007/s10533-016-0219-3", "https://doi.org/10.1088/1748-9326/10/9/094008", "https://doi.org/10.1016/j.agrformet.2015.03.011", "https://doi.org/10.1038/nclimate2253", "https://doi.org/10.1016/j.agrformet.2012.11.023", "https://doi.org/10.1038/nature12291", "https://doi.org/10.1890/12-0893.1", "https://doi.org/10.5194/bg-10-6893-2013", "https://earthdata.nasa.gov/featured-stories/featured-research/secrets-leaves", "https://doi.org/10.1111/j.1365-2486.2012.02678.x", "https://doi.org/10.1111/j.1365-2486.2011.02562.x", "https://doi.org/10.1029/2012JG001960", "https://doi.org/10.1029/2011JG001661", "https://doi.org/10.1029/2009jg001229"]}