{"processing_level_id": "4", "tags": {"org.ceos.wgiss.cwic.granules.prod": {}, "edsc.extra.serverless.collection_capabilities": {"data": {"cloud_cover": true, "day_night_flag": true, "granule_online_access_flag": false, "orbit_calculated_spatial_domains": false}}}, "boxes": ["-90 -180 90 180"], "time_start": "1999-12-18T00:00:00.000Z", "version_id": "055", "updated": "2018-08-13T11:27:05.009Z", "dataset_id": "MODIS/Terra Net Primary Production Yearly L4 Global 1km SIN Grid V055", "has_spatial_subsetting": false, "has_transforms": false, "has_variables": false, "data_center": "LPDAAC_ECS", "short_name": "MOD17A3", "organizations": ["LP DAAC", "NASA/GSFC/SED/ESD/TISL/MODAPS"], "title": "MODIS/Terra Net Primary Production Yearly L4 Global 1km SIN Grid V055", "coordinate_system": "CARTESIAN", "summary": "The MOD17A3.055 dataset was decommissioned on April 6, 2020. Users are encouraged to use the new improved MOD17A3HGF.006 dataset.\r\n\r\nThe Moderate Resolution Imaging Spectroradiometer (MODIS) Net Primary Productivity (NPP) product (MOD17A3) defines the rate at which all plants in an ecosystem produce net useful chemical energy. In other words, NPP is equal to the difference between the rate at which plants in an ecosystem produce useful chemical energy or Gross Primary Productivity (GPP), and the rate at which they expend some of that energy for respiration.  \r\n\r\nVersion 5.5 of the NPP product is produced by the Numerical Terradynamic Simulation Group (NTSG) at the University of Montana (UMT). It corrects the problem with cloud-contaminated MODIS Leaf Area Index (LAI)/Fraction of Photosynthetically Active Radiation (FPAR) inputs to the MOD17 algorithm. The original, uncorrected datasets constitute the Version 4 NPP products. For further details regarding the differences between the NTSG and NASA versions of this product, please consult the document referenced in the following news release: (Terra MODIS GPP/NPP Products from NTSG/University of Montana) (https://lpdaac.usgs.gov/about/news_archive/terra_modis_gppnpp_products_ntsguniversity_montana).  \r\n\r\nVersion 5.5 Terra MODIS NPP products are validated to stage 3. This means that its accuracy was assessed and uncertainties in the product were well established via independent measurements made in a systematic and statistically robust way that represents global conditions. These data are deemed ready for use in science applications.\r\n\r\nThe following data citation is recommended when using MOD17A3 data:\r\nRunning, S., Mu, Q., Zhao, M. (2011). MOD17A3 MODIS/Terra Net Primary Production Yearly L4 Global 1km SIN Grid V055 [Data set]. NASA EOSDIS Land Processes DAAC.\r\n\r\n", "has_granules": true, "orbit_parameters": {}, "id": "C198653829-LPDAAC_ECS", "has_formats": false, "original_format": "UMM_JSON", "granule_count": 4290, "archive_center": "LP DAAC", "has_temporal_subsetting": false, "browse_flag": false, "online_access_flag": false, "links": [{"rel": "http://esipfed.org/ns/fedsearch/1.1/documentation#", "hreflang": "en-US", "href": "http://landweb.nascom.nasa.gov/cgi-bin/QA_WWW/qaFlagPage.cgi?sat=terra&ver=C5"}, {"rel": "http://esipfed.org/ns/fedsearch/1.1/documentation#", "hreflang": "en-US", "href": "https://lpdaac.usgs.gov/products/mod17a3v055/"}, {"rel": "http://esipfed.org/ns/fedsearch/1.1/documentation#", "hreflang": "en-US", "href": "https://lpdaac.usgs.gov/documents/212/mod17_v5_user_guide.pdf"}, {"rel": "http://esipfed.org/ns/fedsearch/1.1/documentation#", "hreflang": "en-US", "href": "https://lpdaac.usgs.gov/documents/213/mod17_v5_atbd.pdf"}], "cmr": {"title": "MODIS/Terra Net Primary Production Yearly L4 Global 1km SIN Grid V055", "summary": "The MOD17A3.055 dataset was decommissioned on April 6, 2020. Users are encouraged to use the new improved MOD17A3HGF.006 dataset.\r\n\r\nThe Moderate Resolution Imaging Spectroradiometer (MODIS) Net Primary Productivity (NPP) product (MOD17A3) defines the rate at which all plants in an ecosystem produce net useful chemical energy. In other words, NPP is equal to the difference between the rate at which plants in an ecosystem produce useful chemical energy or Gross Primary Productivity (GPP), and the rate at which they expend some of that energy for respiration.  \r\n\r\nVersion 5.5 of the NPP product is produced by the Numerical Terradynamic Simulation Group (NTSG) at the University of Montana (UMT). It corrects the problem with cloud-contaminated MODIS Leaf Area Index (LAI)/Fraction of Photosynthetically Active Radiation (FPAR) inputs to the MOD17 algorithm. The original, uncorrected datasets constitute the Version 4 NPP products. For further details regarding the differences between the NTSG and NASA versions of this product, please consult the document referenced in the following news release: (Terra MODIS GPP/NPP Products from NTSG/University of Montana) (https://lpdaac.usgs.gov/about/news_archive/terra_modis_gppnpp_products_ntsguniversity_montana).  \r\n\r\nVersion 5.5 Terra MODIS NPP products are validated to stage 3. This means that its accuracy was assessed and uncertainties in the product were well established via independent measurements made in a systematic and statistically robust way that represents global conditions. These data are deemed ready for use in science applications.\r\n\r\nThe following data citation is recommended when using MOD17A3 data:\r\nRunning, S., Mu, Q., Zhao, M. (2011). MOD17A3 MODIS/Terra Net Primary Production Yearly L4 Global 1km SIN Grid V055 [Data set]. NASA EOSDIS Land Processes DAAC.\r\n\r\n", "id": "C198653829-LPDAAC_ECS", "description": "The MOD17A3.055 dataset was decommissioned on April 6, 2020. Users are encouraged to use the new improved MOD17A3HGF.006 dataset.\r\n\r\nThe Moderate Resolution Imaging Spectroradiometer (MODIS) Net Primary Productivity (NPP) product (MOD17A3) defines the rate at which all plants in an ecosystem produce net useful chemical energy. In other words, NPP is equal to the difference between the rate at which plants in an ecosystem produce useful chemical energy or Gross Primary Productivity (GPP), and the rate at which they expend some of that energy for respiration.  \r\n\r\nVersion 5.5 of the NPP product is produced by the Numerical Terradynamic Simulation Group (NTSG) at the University of Montana (UMT). It corrects the problem with cloud-contaminated MODIS Leaf Area Index (LAI)/Fraction of Photosynthetically Active Radiation (FPAR) inputs to the MOD17 algorithm. The original, uncorrected datasets constitute the Version 4 NPP products. For further details regarding the differences between the NTSG and NASA versions of this product, please consult the document referenced in the following news release: (Terra MODIS GPP/NPP Products from NTSG/University of Montana) (https://lpdaac.usgs.gov/about/news_archive/terra_modis_gppnpp_products_ntsguniversity_montana).  \r\n\r\nVersion 5.5 Terra MODIS NPP products are validated to stage 3. This means that its accuracy was assessed and uncertainties in the product were well established via independent measurements made in a systematic and statistically robust way that represents global conditions. These data are deemed ready for use in science applications.\r\n\r\nThe following data citation is recommended when using MOD17A3 data:\r\nRunning, S., Mu, Q., Zhao, M. (2011). MOD17A3 MODIS/Terra Net Primary Production Yearly L4 Global 1km SIN Grid V055 [Data set]. NASA EOSDIS Land Processes DAAC.\r\n\r\n", "spatialExtent": "N: 90.0 S: -90.0 E: 180.0 W: -180.0", "dataFormat": null, "temporalExtent": "1999-12-18 to now", "Platform": "Terra", "Data Center": "LP DAAC", "Instrument": "MODIS", "Version": "055", "ScienceKeywords1": "EARTH SCIENCE@BIOSPHERE@ECOLOGICAL DYNAMICS@PHOTOSYNTHESIS", "ScienceKeywords2": "EARTH SCIENCE@BIOSPHERE@ECOLOGICAL DYNAMICS@PRIMARY PRODUCTION", "ScienceKeywords3": null, "ScienceKeywords4": null}}